setup.py
get_time/__init__.py
get_time_uu.egg-info/PKG-INFO
get_time_uu.egg-info/SOURCES.txt
get_time_uu.egg-info/dependency_links.txt
get_time_uu.egg-info/entry_points.txt
get_time_uu.egg-info/top_level.txt