Metadata-Version: 2.1
Name: get-time-uu
Version: 0.0.4
Summary: 获取任意时间/获取当前的时间戳/时间转时间戳/时间戳转时间
Home-page: https://github.com/Coxhuang/get_time
Author: 黄民航
Author-email: gmhesat@gmail.com
License: UNKNOWN
Platform: UNKNOWN
